coca_line/__init__.py
coca_line/client.py
coca_line-0.1.1.dist-info/LICENSE
coca_line-0.1.1.dist-info/METADATA
coca_line-0.1.1.dist-info/WHEEL
coca_line-0.1.1.dist-info/RECORD
