Metadata-Version: 2.1
Name: coca-line
Version: 0.1.1
Summary: 
Home-page: https://github.com/CocaButon60s/coca_line
License: MIT
Author: Hiroyuki Ikuno
Author-email: sam2kaikaramegusuri@gmail.com
Requires-Python: >=3.11,<4.0
Classifier: License :: OSI Approved :: MIT License
Classifier: Programming Language :: Python :: 3
Classifier: Programming Language :: Python :: 3.11
Requires-Dist: requests (>=2.31.0,<3.0.0)
